__init__.py
litmos/__init__.py
litmos/api.py
litmos/course.py
litmos/course_module.py
litmos/litmos.py
litmos/team.py
litmos/team_hierarchy.py
litmos/user.py
litmos_api-1.3.0.dist-info/AUTHORS.rst
litmos_api-1.3.0.dist-info/LICENSE
litmos_api-1.3.0.dist-info/METADATA
litmos_api-1.3.0.dist-info/WHEEL
litmos_api-1.3.0.dist-info/top_level.txt
litmos_api-1.3.0.dist-info/RECORD
