Metadata-Version: 2.1
Name: litmos-api
Version: 1.3.0
Summary: Python client for Litmos (LMS) API
Home-page: https://github.com/charliequinn/python-litmos-api
Author: Charlie Quinn
Author-email: charlesquinn1984@gmail.com
License: BSD
Keywords: litmos,API
Platform: UNKNOWN
Classifier: Development Status :: 5 - Production/Stable
Classifier: Intended Audience :: Developers
Classifier: License :: OSI Approved :: BSD License
Classifier: Operating System :: Unix
Classifier: Programming Language :: Python
Classifier: Programming Language :: Python :: 3.6
Classifier: Programming Language :: Python :: 3.7
Classifier: Programming Language :: Python :: 3.8
Classifier: Topic :: Utilities
Requires-Dist: requests (==2.24.0)
Requires-Dist: inflect (==4.1.0)
Requires-Dist: treelib (==1.6.1)
